README.txt
setup.py
src/gocept/__init__.py
src/gocept.cmmi.egg-info/PKG-INFO
src/gocept.cmmi.egg-info/SOURCES.txt
src/gocept.cmmi.egg-info/dependency_links.txt
src/gocept.cmmi.egg-info/entry_points.txt
src/gocept.cmmi.egg-info/namespace_packages.txt
src/gocept.cmmi.egg-info/requires.txt
src/gocept.cmmi.egg-info/top_level.txt
src/gocept/cmmi/__init__.py