Metadata-Version: 1.0
Name: gocept.cmmi
Version: 0.9.4
Summary: **Deprecated** zc.buildout recipe for building a software package from source.
Home-page: http://svn.gocept.com/repos/gocept/buildout-recipes/gocept.cmmi
Author: Thomas Lotze
Author-email: tl@gocept.com
License: ZPL 2.1
Keywords: buildout
Platform: UNKNOWN
Classifier: Framework :: Buildout
